snapcache/__init__.py
snapcache-1.0.0.dist-info/LICENSE
snapcache-1.0.0.dist-info/METADATA
snapcache-1.0.0.dist-info/WHEEL
snapcache-1.0.0.dist-info/RECORD
