Metadata-Version: 2.1
Name: snapcache
Version: 1.0.0
Summary: Snap-in memory caching for Python, no persistence, just pure function result caching.
Home-page: https://del.wang
License: MIT
Keywords: cache,functools,lru_cache,unhashable
Author: Del Wang
Author-email: hello@xbox.work
Maintainer: Del Wang
Maintainer-email: hello@xbox.work
Requires-Python: >=3.8,<4.0
Classifier: License :: OSI Approved :: MIT License
Classifier: Programming Language :: Python :: 3
Classifier: Programming Language :: Python :: 3.8
Classifier: Programming Language :: Python :: 3.9
Classifier: Programming Language :: Python :: 3.10
Classifier: Programming Language :: Python :: 3.11
Classifier: Programming Language :: Python :: 3.12
Classifier: Programming Language :: Python :: 3.13
Project-URL: Changelog, https://github.com/idootop/snapcache/blob/main/CHANGELOG.md
Project-URL: Documentation, https://github.com/idootop/snapcache/README.md
Project-URL: Repository, https://github.com/idootop/snapcache
